setup.py
stringhelpers/__init__.py
stringhelpers.egg-info/PKG-INFO
stringhelpers.egg-info/SOURCES.txt
stringhelpers.egg-info/dependency_links.txt
stringhelpers.egg-info/not-zip-safe
stringhelpers.egg-info/top_level.txt