Metadata-Version: 1.0
Name: stringhelpers
Version: 1.0
Summary: A set of various string helpers.
Home-page: https://github.com/skaflem/stringhelpers
Author: Thomas Skaflem
Author-email: thomas@skaflem.net
License: MIT
Platform: UNKNOWN
Classifier: Topic :: Utilities
Classifier: Topic :: Text Processing
Classifier: Intended Audience :: Developers
Classifier: Operating System :: OS Independent
Classifier: Programming Language :: Python :: 2
Classifier: Programming Language :: Python :: 3
Classifier: License :: OSI Approved :: MIT License
